{
  "montebello": "069009",
  "montebellosulsangro": "069009",
  "canosa": "069010",
  "canosasannita": "069010",
  "carpineto": "069011",
  "carpinetosinello": "069011",
  "castel": "069018",
  "castelfrentano": "069018",
  "castiglione": "069020",
  "castiglione messer": "069020",
  "castiglionemesser": "069020",
  "castiglionemessermarino": "069020",
  "celenza": "069021",
  "celenzasultrigno": "069021",
  "civitella": "069024",
  "civitella messer": "069024",
  "civitellamesser": "069024",
  "civitellamesserraimondo": "069024",
  "fara filiorum": "069030",
  "farafiliorum": "069030",
  "farafiliorumpetri": "069030",
  "fara san": "069031",
  "farasan": "069031",
  "farasanmartino": "069031",
  "francavilla": "069035",
  "francavilla al": "069035",
  "francavillaal": "069035",
  "francavillaalmare": "069035",
  "giuliano": "069042",
  "giulianoteatino": "069042",
  "lama": "069045",
  "lamadeipeligni": "069045",
  "ripa": "069072",
  "ripateatina": "069072",
  "rocca": "069074",
  "rocca san": "069074",
  "roccasan": "069074",
  "roccasangiovanni": "069074",
  "roio": "069077",
  "roiodelsangro": "069077",
  "sanbuono": "069079",
  "sangiovannilipioni": "069080",
  "sangiovanniteatino": "069081",
  "san martino": "069082",
  "sanmartino": "069082",
  "sanmartinosullamarrucina": "069082",
  "sansalvo": "069083",
  "santa": "069084",
  "santa maria": "069084",
  "santamaria": "069084",
  "santamariaimbaro": "069084",
  "sant": "069085",
  "sant eusanio": "069085",
  "santeusanio": "069085",
  "santeusaniodelsangro": "069085",
  "san vito": "069086",
  "sanvito": "069086",
  "sanvitochietino": "069086",
  "schiavi": "069088",
  "schiavidiabruzzo": "069088",
  "taranta": "069089",
  "tarantapeligna": "069089",
  "torino": "069091",
  "torinodisangro": "069091",
  "torrevecchia": "069094",
  "torrevecchiateatina": "069094",
  "torricella": "069095",
  "torricellapeligna": "069095",
  "villa": "069102",
  "villa santa": "069102",
  "villasanta": "069102",
  "villasantamaria": "069102"
}
